Decode/src/control.v
module control{
    input wire clk, rst 
    input wire [5:0] opcode; 
    output reg [1:0] wb, 
    output reg [2:0] mem, 
    output reg [3:0] ex 
}; 

    parameter RTYPE = 6'b000000; 
    parameter LW = 6'b100011;
    parameter SW = 6'b101011; 
    parameter BEQ = 6'b000100; 
    parameter NOP = 6'b100000; 

    initial begin 
        wb = 2'd0; 
        mem = 3'd0; 
        ex = 4'd0; 
    end

    always @(posedge clk)begin
        if (rst) begin
            wb = 2'd0; 
            mem = 3'd0; 
            ex = 4'd0; 
        end

        case(opcode)
            RTYPE: begin 
                wb <= 2'b10; 
                mem <= 3'b000; 
                ex <= 4'b1100; 
            end
            LW: begin
                wb <= 2'b11; 
                mem <= 3'b010; 
                ex <= 4'b0001;
            end
            SW: begin
                wb <= 2'bx; 
                mem <= 3'b001; 
                ex <= 4'bx001;
            end
            BEQ: begin
                wb <= 2'bx; 
                mem <= 3'b100; 
                ex <= 4'bx010;
            end
            default: begin
                $display("Opcode not recognized.");
                wb <= 2'd0; 
                mem <= 3'd0; 
                ex <= 4'd0; 
            end
        endcase 
    end

endmodule

Decode/sim/controlTB.v
`timescale 1ns / 1ps
`include "../src/controlTB.v"

module controlTB;

    wire [1:0] wb; 
    wire [2:0] mem; 
    wire [3:0] ex; 
    reg clk, rst; 
    reg [5:0] opcode; 

    control DUT (
        .wb(wb), 
        .mem(mem), 
        .ex(ex), 
        .clk(clk), 
        .rst(rst), 
        .opcode(opcode)
    ); 

    initial begin 
        $dumpfile("controlTB.vcd"); 
        $dumpvars(0, controlTB);
        end

    parameter RTYPE = 6'b000000; 
    parameter LW = 6'b100011;
    parameter SW = 6'b101011; 
    parameter BEQ = 6'b000100; 
    parameter NOP = 6'b100000; 

    initial begin 
        clk = 0; 
        forever #1 clk = ~clk; 
    end

    initial begin 
        rst = 1; 
        opcode = RTYPE; 
        #2; 

        rst = 0; 
        #2; 
        opcode = LW; 
        #2; 
        opcode = SW; 
        #2;
        opcode = BEQ; 
        #2; 
        opcode = NOP;
        #2;
        opcode = 6'b111100;
        #2;
        $display("Test Complete"); 

        $finish   
    end

    initial begin 
        $monitor("Time=%0t opcode=%b wb=%b mem=%b ex=%b rst=%b", 
        $time, opcode, wb, mem, ex, rst);

    end
endmodule

Decode/sim/controlTB.vcd
$date
	Sat Mar 21 14:30:06 2026
$end
$version
	Icarus Verilog
$end
$timescale
	1ps
$end
$scope module controlTB $end
$var wire 2 ! wb [1:0] $end
$var wire 3 " mem [2:0] $end
$var wire 4 # ex [3:0] $end
$var parameter 6 $ BEQ $end
$var parameter 6 % LW $end
$var parameter 6 & NOP $end
$var parameter 6 ' RTYPE $end
$var parameter 6 ( SW $end
$var reg 1 ) clk $end
$var reg 6 * opcode [5:0] $end
$var reg 1 + rst $end
$scope module DUT $end
$var wire 1 ) clk $end
$var wire 6 , opcode [5:0] $end
$var wire 1 + rst $end
$var parameter 6 - BEQ $end
$var parameter 6 . LW $end
$var parameter 6 / NOP $end
$var parameter 6 0 RTYPE $end
$var parameter 6 1 SW $end
$var reg 4 2 ex [3:0] $end
$var reg 3 3 mem [2:0] $end
$var reg 2 4 wb [1:0] $end
$upscope $end
$upscope $end
$enddefinitions $end
$comment Show the parameter values. $end
$dumpall
b101011 1
b0 0
b100000 /
b100011 .
b100 -
b101011 (
b0 '
b100000 &
b100011 %
b100 $
$end
#0
$dumpvars
b0 4
b0 3
b0 2
b0 ,
1+
b0 *
0)
b0 #
b0 "
b0 !
$end
#1000
1)
#2000
0)
0+
#3000
b1100 #
b1100 2
b10 !
b10 4
1)
#4000
0)
b100011 *
b100011 ,
#5000
b1 #
b1 2
b100 "
b100 3
b11 !
b11 4
1)
#6000
0)
b101011 *
b101011 ,
#7000
b10 "
b10 3
b0 !
b0 4
1)
#8000
0)
b100 *
b100 ,
#9000
b10 #
b10 2
b1 "
b1 3
1)
#10000
0)
b100000 *
b100000 ,
#11000
b0 #
b0 2
b0 "
b0 3
1)
#12000
0)
b111100 *
b111100 ,
