Instruction-Fetch/ifIdLatch.v
module ifIdLatch (
    input wire clk,rst,
    input wire [31:0] d,
    output reg [31:0] q
);
    always @(posedge clk or posedge rst) begin
        if (rst) begin
            q <= 0;
        end else begin
            q<=d;
        end
    end

endmodule

Instruction-Fetch/mux.v
module mux(
    input wire PCSrc,
    input wire [31:0] PC_from_ExMem, Incremented_PC,
    output wire [31:0] address
);
    assign address = (PCSrc ? PC_from_ExMem : Incremented_PC);
    
endmodule

Instruction-Fetch/incrementer.v
module incrementer(
    input wire clk, rst,
    input wire [31:0] pc,
    output reg [31:0] incremented_pc
);
    always @(posedge clk or posedge rst) begin
        if (rst) begin
            incremented_pc<=0;
        end else begin
            incremented_pc <= pc+1; //should be add 4 bytes because each instr is 4 bytes, ignore for now
        end
    end
endmodule

Instruction-Fetch/instrMem.v
module instrMem#(parameter MEM_SIZE = 2**32) (
    input wire clk, rst,
    input wire [31:0] addr,
    output reg [31:0] instr
);
    reg [31:0] memory [0:MEM_SIZE-1]; //32 bit word, 2^32 slots


    always @(posedge clk or posedge rst) begin
        if (rst) begin
            memory[0] <= 32'hA00000AA;
            memory[1] <= 32'h10000011;
            memory[2] <= 32'h20000022;
            memory[3] <= 32'h30000033;
            memory[4] <= 32'h40000044;
            memory[5] <= 32'h50000055;
            memory[6] <= 32'h60000066;
            memory[7] <= 32'h70000077;
            memory[8] <= 32'h80000088;
            memory[9] <= 32'h90000099;
            instr <= 32'hA00000AA;
        end else begin
            instr <= memory[addr];
        end
    end
endmodule

Instruction-Fetch/pc.v
module pc (
    input wire [31:0] in,
    output reg [31:0] out,
    input wire clk
);
    always @(posedge clk) begin
        out <= in;
    end
endmodule

Instruction-Fetch/fetch.v
module fetch(
    input wire clk,rst,ex_mem_pc_src,
    input wire [31:0] ex_mem_npc,
    output wire [31:0] if_id_instr, if_id_npc
);

    // output declaration of module pc
    wire [31:0] pc_out;
    wire [31:0] instr;
    wire [31:0] incremented_pc;
    wire [31:0] pc_next;
    
    pc u_pc(
        .in  	(pc_next   ),
        .out 	(pc_out  ),
        .clk 	(clk  )
    );
    
    instrMem #(.MEM_SIZE 	(2**16)) u_instrMem(
        .clk   	(clk    ),
        .addr  	(pc_out   ),
        .instr 	(instr  )
    );
    
    incrementer u_incrementer(
        .rst                (rst),
        .clk            	(clk             ),
        .pc             	(pc_out      ),
        .incremented_pc 	(incremented_pc  )
    );
    
    mux u_mux(
        .Incremented_PC(incremented_pc),
        .PCSrc(ex_mem_pc_src),
        .PC_from_ExMem(ex_mem_npc),
        .address 	(pc_next  )
    );
    
    ifIdLatch u_instrMem_Latch(
        .rst    (       rst) ,
        .clk 	(clk  ),
        .d   	(instr    ),
        .q   	(if_id_instr    )
    );
    
    ifIdLatch u_incremented_pc_Latch(
        .rst    (rst  ),
        .clk 	(clk  ),
        .d   	(incremented_pc    ),
        .q   	(if_id_npc    )
    );
    
    

endmodule

Instruction-Fetch/fetchtb.v
`timescale 1ns/1ps

module fetchtb ();
    wire [31:0] ex_mem_npc = 0;
    wire [31:0] if_id_instr;
    wire [31:0] if_id_npc;
    reg clk,rst;
    reg ex_mem_pc_src;
    
    fetch u_fetch(
        .clk           	(clk            ),
        .rst           	(rst            ),
        .ex_mem_pc_src 	(ex_mem_pc_src  ),
        .ex_mem_npc    	(ex_mem_npc     ),
        .if_id_instr   	(if_id_instr    ),
        .if_id_npc     	(if_id_npc      )
    );
    
    
    initial begin
        clk = 0;

        forever #5 clk = ~clk;
    end 

    initial begin

        //initial values
        $dumpfile("fetchtb.vcd");
        $dumpvars(0, fetchtb);
        rst = 1;
        ex_mem_pc_src = 1;
        #10 
        rst = 0;
        ex_mem_pc_src = 0;
        #100
        $finish;
    end

    initial begin
        $monitor("Instr = %h, PC = %h",if_id_instr,if_id_npc);
    end
endmodule

Instruction-Fetch/fetchtb.vcd
$date
	Sun Mar 15 02:31:50 2026
$end
$version
	Icarus Verilog
$end
$timescale
	1ps
$end
$scope module fetchtb $end
$var wire 32 ! ex_mem_npc [31:0] $end
$var wire 32 " if_id_npc [31:0] $end
$var wire 32 # if_id_instr [31:0] $end
$var reg 1 $ clk $end
$var reg 1 % ex_mem_pc_src $end
$var reg 1 & rst $end
$scope module u_fetch $end
$var wire 1 $ clk $end
$var wire 32 ' ex_mem_npc [31:0] $end
$var wire 1 % ex_mem_pc_src $end
$var wire 1 & rst $end
$var wire 32 ( pc_out [31:0] $end
$var wire 32 ) pc_next [31:0] $end
$var wire 32 * instr [31:0] $end
$var wire 32 + incremented_pc [31:0] $end
$var wire 32 , if_id_npc [31:0] $end
$var wire 32 - if_id_instr [31:0] $end
$scope module u_incremented_pc_Latch $end
$var wire 1 $ clk $end
$var wire 1 & rst $end
$var wire 32 . d [31:0] $end
$var reg 32 / q [31:0] $end
$upscope $end
$scope module u_incrementer $end
$var wire 1 $ clk $end
$var wire 1 & rst $end
$var wire 32 0 pc [31:0] $end
$var reg 32 1 incremented_pc [31:0] $end
$upscope $end
$scope module u_instrMem $end
$var wire 1 $ clk $end
$var wire 1 2 rst $end
$var wire 32 3 addr [31:0] $end
$var parameter 32 4 MEM_SIZE $end
$var reg 32 5 instr [31:0] $end
$upscope $end
$scope module u_instrMem_Latch $end
$var wire 1 $ clk $end
$var wire 32 6 d [31:0] $end
$var wire 1 & rst $end
$var reg 32 7 q [31:0] $end
$upscope $end
$scope module u_mux $end
$var wire 32 8 Incremented_PC [31:0] $end
$var wire 1 % PCSrc $end
$var wire 32 9 PC_from_ExMem [31:0] $end
$var wire 32 : address [31:0] $end
$upscope $end
$scope module u_pc $end
$var wire 1 $ clk $end
$var wire 32 ; in [31:0] $end
$var reg 32 < out [31:0] $end
$upscope $end
$upscope $end
$upscope $end
$enddefinitions $end
$comment Show the parameter values. $end
$dumpall
b10000000000000000 4
$end
#0
$dumpvars
bx <
b0 ;
b0 :
b0 9
b0 8
b0 7
bx 6
bx 5
bx 3
z2
b0 1
bx 0
b0 /
b0 .
b0 -
b0 ,
b0 +
bx *
b0 )
bx (
b0 '
1&
1%
0$
b0 #
b0 "
b0 !
$end
#5000
b0 (
b0 0
b0 3
b0 <
1$
#10000
0$
0%
0&
#15000
b1 )
b1 :
b1 ;
b1 +
b1 .
b1 1
b1 8
bx #
bx -
bx 7
1$
#20000
0$
#25000
b1 "
b1 ,
b1 /
b1 (
b1 0
b1 3
b1 <
1$
#30000
0$
#35000
b10 )
b10 :
b10 ;
b10 +
b10 .
b10 1
b10 8
1$
#40000
0$
#45000
b10 "
b10 ,
b10 /
b10 (
b10 0
b10 3
b10 <
1$
#50000
0$
#55000
b11 )
b11 :
b11 ;
b11 +
b11 .
b11 1
b11 8
1$
#60000
0$
#65000
b11 "
b11 ,
b11 /
b11 (
b11 0
b11 3
b11 <
1$
#70000
0$
#75000
b100 )
b100 :
b100 ;
b100 +
b100 .
b100 1
b100 8
1$
#80000
0$
#85000
b100 "
b100 ,
b100 /
b100 (
b100 0
b100 3
b100 <
1$
#90000
0$
#95000
b101 )
b101 :
b101 ;
b101 +
b101 .
b101 1
b101 8
1$
#100000
0$
#105000
b101 "
b101 ,
b101 /
b101 (
b101 0
b101 3
b101 <
1$
