Instruction-Fetch/ifIdLatch.v
module ifIdLatch (
    input wire clk,rst,
    input wire [31:0] d,
    output reg [31:0] q
);
    always @(posedge clk or posedge rst) begin
        if (rst) begin
            q <= 1;
        end else begin
            q<=d;
        end
    end

endmodule

Instruction-Fetch/mux.v
module mux(
    input wire PCSrc,
    input wire [31:0] PC_from_ExMem, Incremented_PC,
    output wire [31:0] address
);
    assign address = (PCSrc ? PC_from_ExMem : Incremented_PC);
    
endmodule

Instruction-Fetch/incrementer.v
module incrementer(
    input wire [31:0] pc,
    output reg [31:0] incremented_pc
);
    always @(*) begin
        incremented_pc = pc+1; //should be add 4 bytes because each instr is 4 bytes, ignore for now
    end
endmodule

Instruction-Fetch/instrMem.v
module instrMem#(parameter MEM_SIZE = 2**16) (
    input wire clk, rst,
    input wire [31:0] addr,
    output reg [31:0] instr
);
    reg [31:0] memory [0:MEM_SIZE-1];

    always @(posedge clk or posedge rst) begin
        if (rst) begin
            memory[0] <= 32'b100011_00000_00001_0000_0000_0000_0001;
            memory[1] <= 32'b100011_00000_00010_0000_0000_0000_0010;
            memory[2] <= 32'b100011_00000_00011_0000_0000_0000_0011;
            memory[3] <= 32'b1000_0000_0000_0000_0000_0000_0000_0000;
            memory[4] <= 32'b1000_0000_0000_0000_0000_0000_0000_0000;
            memory[5] <= 32'b000000_00001_00010_00001_00000_100000;
           // memory[6] <= 32'b1000_0000_0000_0000_0000_0000_0000_0000;
           // memory[7] <= 32'b1000_0000_0000_0000_0000_0000_0000_0000;
           // memory[8] <= 32'b1000_0000_0000_0000_0000_0000_0000_0000;
            memory[6] <= 32'b000000_00001_00011_00001_00000_100000;
            // memory[10] <= 32'b1000_0000_0000_0000_0000_0000_0000_0000;
            // memory[11] <= 32'b1000_0000_0000_0000_0000_0000_0000_0000;
            // memory[12] <= 32'b1000_0000_0000_0000_0000_0000_0000_0000;
            memory[7] <= 32'b000000_00001_00001_00001_00000_100000;
            // memory[14] <= 32'b1000_0000_0000_0000_0000_0000_0000_0000;
            // memory[15] <= 32'b1000_0000_0000_0000_0000_0000_0000_0000;
            // memory[16] <= 32'b1000_0000_0000_0000_0000_0000_0000_0000;
            // memory[17] <= 32'b1000_0000_0000_0000_0000_0000_0000_0000;
            memory[8] <= 32'b000000_00001_00000_00001_00000_100000;
            // memory[19] <= 32'b1000_0000_0000_0000_0000_0000_0000_0000;
            // memory[20] <= 32'b1000_0000_0000_0000_0000_0000_0000_0000;
            // memory[21] <= 32'b1000_0000_0000_0000_0000_0000_0000_0000;
            // memory[22] <= 32'b1000_0000_0000_0000_0000_0000_0000_0000;
            // memory[23] <= 32'b1000_0000_0000_0000_0000_0000_0000_0000;
        end
    end

    always @(*) begin
        instr = memory[addr];
    end

endmodule

Instruction-Fetch/pc.v
module pc (
    input wire rst,
    input wire [31:0] in,
    output reg [31:0] out,
    input wire clk
);
    always @(posedge clk or posedge rst) begin
        if (rst) begin
            out <= 0;
        end else begin
            out <= in;
        end
    end
endmodule

Instruction-Fetch/fetch.v
module fetch(
    input wire clk,rst,ex_mem_pc_src,
    input wire [31:0] ex_mem_npc,
    output wire [31:0] if_id_instr, if_id_npc
);

    // output declaration of module pc
    wire [31:0] pc_out;
    wire [31:0] instr;
    wire [31:0] incremented_pc;
    wire [31:0] pc_next;
    
    pc u_pc(
        .rst    (rst       ),
        .in  	(pc_next   ),
        .out 	(pc_out  ),
        .clk 	(clk  )
    );
    
    instrMem #(.MEM_SIZE 	(2**16)) u_instrMem(
        .clk   	(clk    ),
        .rst    (rst    ), 
        .addr  	(pc_out   ),
        .instr 	(instr  )
    );
    
    incrementer u_incrementer(
        .pc             	(pc_out      ),
        .incremented_pc 	(incremented_pc  )
    );
    
    mux u_mux(
        .Incremented_PC(incremented_pc),
        .PCSrc(ex_mem_pc_src),
        .PC_from_ExMem(ex_mem_npc),
        .address 	(pc_next  )
    );
    
    ifIdLatch u_instrMem_Latch(
        .rst    (       rst) ,
        .clk 	(clk  ),
        .d   	(instr    ),
        .q   	(if_id_instr    )
    );
    
    ifIdLatch u_incremented_pc_Latch(
        .rst    (rst  ),
        .clk 	(clk  ),
        .d   	(incremented_pc    ),
        .q   	(if_id_npc    )
    );
    
    

endmodule

Instruction-Fetch/fetchtb.v
`timescale 1ns/1ps

module fetchtb ();
    wire [31:0] ex_mem_npc = 32'h0000_0000;
    wire [31:0] if_id_instr;
    wire [31:0] if_id_npc;
    reg clk,rst;
    reg ex_mem_pc_src;
    
    fetch u_fetch(
        .clk           	(clk            ),
        .rst           	(rst            ),
        .ex_mem_pc_src 	(ex_mem_pc_src  ),
        .ex_mem_npc    	(ex_mem_npc     ),
        .if_id_instr   	(if_id_instr    ),
        .if_id_npc     	(if_id_npc      )
    );
    
    
    initial begin
        clk = 0;

        forever #5 clk = ~clk;
    end 

    initial begin

        //initial values
        $dumpfile("fetchtb.vcd");
        $dumpvars(0, fetchtb);
        rst = 1;
        ex_mem_pc_src = 0;
        #5 
        rst = 0;
        #45
        ex_mem_pc_src = 1;
        #10
        ex_mem_pc_src = 0;
        #125
        $finish;
    end

    initial begin
        $monitor("Instr = %h, Next_PC = %h",if_id_instr,if_id_npc);
    end
endmodule

Instruction-Fetch/fetchtb.vcd
$date
	Thu Mar 19 00:18:54 2026
$end
$version
	Icarus Verilog
$end
$timescale
	1ps
$end
$scope module fetchtb $end
$var wire 32 ! ex_mem_npc [31:0] $end
$var wire 32 " if_id_npc [31:0] $end
$var wire 32 # if_id_instr [31:0] $end
$var reg 1 $ clk $end
$var reg 1 % ex_mem_pc_src $end
$var reg 1 & rst $end
$scope module u_fetch $end
$var wire 1 $ clk $end
$var wire 32 ' ex_mem_npc [31:0] $end
$var wire 1 % ex_mem_pc_src $end
$var wire 1 & rst $end
$var wire 32 ( pc_out [31:0] $end
$var wire 32 ) pc_next [31:0] $end
$var wire 32 * instr [31:0] $end
$var wire 32 + incremented_pc [31:0] $end
$var wire 32 , if_id_npc [31:0] $end
$var wire 32 - if_id_instr [31:0] $end
$scope module u_incremented_pc_Latch $end
$var wire 1 $ clk $end
$var wire 1 & rst $end
$var wire 32 . d [31:0] $end
$var reg 32 / q [31:0] $end
$upscope $end
$scope module u_incrementer $end
$var wire 32 0 pc [31:0] $end
$var reg 32 1 incremented_pc [31:0] $end
$upscope $end
$scope module u_instrMem $end
$var wire 1 $ clk $end
$var wire 1 & rst $end
$var wire 32 2 addr [31:0] $end
$var parameter 32 3 MEM_SIZE $end
$var reg 32 4 instr [31:0] $end
$upscope $end
$scope module u_instrMem_Latch $end
$var wire 1 $ clk $end
$var wire 32 5 d [31:0] $end
$var wire 1 & rst $end
$var reg 32 6 q [31:0] $end
$upscope $end
$scope module u_mux $end
$var wire 32 7 Incremented_PC [31:0] $end
$var wire 1 % PCSrc $end
$var wire 32 8 PC_from_ExMem [31:0] $end
$var wire 32 9 address [31:0] $end
$upscope $end
$scope module u_pc $end
$var wire 1 $ clk $end
$var wire 32 : in [31:0] $end
$var wire 1 & rst $end
$var reg 32 ; out [31:0] $end
$upscope $end
$upscope $end
$upscope $end
$enddefinitions $end
$comment Show the parameter values. $end
$dumpall
b10000000000000000 3
$end
#0
$dumpvars
b0 ;
b1 :
b1 9
b0 8
b1 7
b1 6
b10100000000000000000000010101010 5
b10100000000000000000000010101010 4
b0 2
b1 1
b0 0
b1 /
b1 .
b1 -
b1 ,
b1 +
b10100000000000000000000010101010 *
b1 )
b0 (
b0 '
1&
0%
0$
b1 #
b1 "
b0 !
$end
#5000
b10 )
b10 9
b10 :
b10 +
b10 .
b10 1
b10 7
b10100000000000000000000010101010 #
b10100000000000000000000010101010 -
b10100000000000000000000010101010 6
b1 (
b1 0
b1 2
b1 ;
0&
1$
#10000
0$
#15000
b11 )
b11 9
b11 :
b11 +
b11 .
b11 1
b11 7
b10 (
b10 0
b10 2
b10 ;
b10000000000000000000000010001 *
b10000000000000000000000010001 4
b10000000000000000000000010001 5
b10 "
b10 ,
b10 /
1$
#20000
0$
#25000
b100 )
b100 9
b100 :
b100 +
b100 .
b100 1
b100 7
b11 "
b11 ,
b11 /
b10000000000000000000000010001 #
b10000000000000000000000010001 -
b10000000000000000000000010001 6
b100000000000000000000000100010 *
b100000000000000000000000100010 4
b100000000000000000000000100010 5
b11 (
b11 0
b11 2
b11 ;
1$
#30000
0$
#35000
b101 )
b101 9
b101 :
b101 +
b101 .
b101 1
b101 7
b100 (
b100 0
b100 2
b100 ;
b110000000000000000000000110011 *
b110000000000000000000000110011 4
b110000000000000000000000110011 5
b100000000000000000000000100010 #
b100000000000000000000000100010 -
b100000000000000000000000100010 6
b100 "
b100 ,
b100 /
1$
#40000
0$
#45000
b110 )
b110 9
b110 :
b110 +
b110 .
b110 1
b110 7
b101 "
b101 ,
b101 /
b110000000000000000000000110011 #
b110000000000000000000000110011 -
b110000000000000000000000110011 6
b1000000000000000000000001000100 *
b1000000000000000000000001000100 4
b1000000000000000000000001000100 5
b101 (
b101 0
b101 2
b101 ;
1$
#50000
b0 )
b0 9
b0 :
0$
1%
#55000
b1 +
b1 .
b1 1
b1 7
b0 (
b0 0
b0 2
b0 ;
b1010000000000000000000001010101 *
b1010000000000000000000001010101 4
b1010000000000000000000001010101 5
b1000000000000000000000001000100 #
b1000000000000000000000001000100 -
b1000000000000000000000001000100 6
b110 "
b110 ,
b110 /
1$
#60000
b1 )
b1 9
b1 :
0$
0%
#65000
b10 )
b10 9
b10 :
b10 +
b10 .
b10 1
b10 7
b1 "
b1 ,
b1 /
b1010000000000000000000001010101 #
b1010000000000000000000001010101 -
b1010000000000000000000001010101 6
b10100000000000000000000010101010 *
b10100000000000000000000010101010 4
b10100000000000000000000010101010 5
b1 (
b1 0
b1 2
b1 ;
1$
#70000
0$
#75000
b11 )
b11 9
b11 :
b11 +
b11 .
b11 1
b11 7
b10 (
b10 0
b10 2
b10 ;
b10000000000000000000000010001 *
b10000000000000000000000010001 4
b10000000000000000000000010001 5
b10100000000000000000000010101010 #
b10100000000000000000000010101010 -
b10100000000000000000000010101010 6
b10 "
b10 ,
b10 /
1$
#80000
0$
#85000
b100 )
b100 9
b100 :
b100 +
b100 .
b100 1
b100 7
b11 "
b11 ,
b11 /
b10000000000000000000000010001 #
b10000000000000000000000010001 -
b10000000000000000000000010001 6
b100000000000000000000000100010 *
b100000000000000000000000100010 4
b100000000000000000000000100010 5
b11 (
b11 0
b11 2
b11 ;
1$
#90000
0$
#95000
b101 )
b101 9
b101 :
b101 +
b101 .
b101 1
b101 7
b100 (
b100 0
b100 2
b100 ;
b110000000000000000000000110011 *
b110000000000000000000000110011 4
b110000000000000000000000110011 5
b100000000000000000000000100010 #
b100000000000000000000000100010 -
b100000000000000000000000100010 6
b100 "
b100 ,
b100 /
1$
#100000
0$
#105000
b110 )
b110 9
b110 :
b110 +
b110 .
b110 1
b110 7
b101 "
b101 ,
b101 /
b110000000000000000000000110011 #
b110000000000000000000000110011 -
b110000000000000000000000110011 6
b1000000000000000000000001000100 *
b1000000000000000000000001000100 4
b1000000000000000000000001000100 5
b101 (
b101 0
b101 2
b101 ;
1$
#110000
0$
#115000
b111 )
b111 9
b111 :
b111 +
b111 .
b111 1
b111 7
b110 (
b110 0
b110 2
b110 ;
b1010000000000000000000001010101 *
b1010000000000000000000001010101 4
b1010000000000000000000001010101 5
b1000000000000000000000001000100 #
b1000000000000000000000001000100 -
b1000000000000000000000001000100 6
b110 "
b110 ,
b110 /
1$
#120000
0$
#125000
b1000 )
b1000 9
b1000 :
b1000 +
b1000 .
b1000 1
b1000 7
b111 "
b111 ,
b111 /
b1010000000000000000000001010101 #
b1010000000000000000000001010101 -
b1010000000000000000000001010101 6
b1100000000000000000000001100110 *
b1100000000000000000000001100110 4
b1100000000000000000000001100110 5
b111 (
b111 0
b111 2
b111 ;
1$
#130000
0$
#135000
b1001 )
b1001 9
b1001 :
b1001 +
b1001 .
b1001 1
b1001 7
b1000 (
b1000 0
b1000 2
b1000 ;
b1110000000000000000000001110111 *
b1110000000000000000000001110111 4
b1110000000000000000000001110111 5
b1100000000000000000000001100110 #
b1100000000000000000000001100110 -
b1100000000000000000000001100110 6
b1000 "
b1000 ,
b1000 /
1$
#140000
0$
#145000
b1010 )
b1010 9
b1010 :
b1010 +
b1010 .
b1010 1
b1010 7
b1001 "
b1001 ,
b1001 /
b1110000000000000000000001110111 #
b1110000000000000000000001110111 -
b1110000000000000000000001110111 6
b10000000000000000000000010001000 *
b10000000000000000000000010001000 4
b10000000000000000000000010001000 5
b1001 (
b1001 0
b1001 2
b1001 ;
1$
#150000
0$
#155000
b1011 )
b1011 9
b1011 :
b1011 +
b1011 .
b1011 1
b1011 7
b1010 (
b1010 0
b1010 2
b1010 ;
b10010000000000000000000010011001 *
b10010000000000000000000010011001 4
b10010000000000000000000010011001 5
b10000000000000000000000010001000 #
b10000000000000000000000010001000 -
b10000000000000000000000010001000 6
b1010 "
b1010 ,
b1010 /
1$
#160000
0$
#165000
b1100 )
b1100 9
b1100 :
b1100 +
b1100 .
b1100 1
b1100 7
b1011 "
b1011 ,
b1011 /
b10010000000000000000000010011001 #
b10010000000000000000000010011001 -
b10010000000000000000000010011001 6
bx *
bx 4
bx 5
b1011 (
b1011 0
b1011 2
b1011 ;
1$
#170000
0$
#175000
b1101 )
b1101 9
b1101 :
b1101 +
b1101 .
b1101 1
b1101 7
b1100 (
b1100 0
b1100 2
b1100 ;
bx #
bx -
bx 6
b1100 "
b1100 ,
b1100 /
1$
#180000
0$
#185000
b1110 )
b1110 9
b1110 :
b1110 +
b1110 .
b1110 1
b1110 7
b1101 "
b1101 ,
b1101 /
b1101 (
b1101 0
b1101 2
b1101 ;
1$
